[
{
  "directory": "C:/Users/ntrem/ECE/Info/TP/build",
  "command": "C:\\mingw64\\bin\\gcc.exe   -g -o CMakeFiles\\TP.dir\\main.c.obj -c C:\\Users\\ntrem\\ECE\\Info\\TP\\main.c",
  "file": "C:/Users/ntrem/ECE/Info/TP/main.c",
  "output": "CMakeFiles/TP.dir/main.c.obj"
},
{
  "directory": "C:/Users/ntrem/ECE/Info/TP/build",
  "command": "C:\\mingw64\\bin\\gcc.exe   -g -o CMakeFiles\\TP.dir\\tp3\\tp3.c.obj -c C:\\Users\\ntrem\\ECE\\Info\\TP\\tp3\\tp3.c",
  "file": "C:/Users/ntrem/ECE/Info/TP/tp3/tp3.c",
  "output": "CMakeFiles/TP.dir/tp3/tp3.c.obj"
},
{
  "directory": "C:/Users/ntrem/ECE/Info/TP/build",
  "command": "C:\\mingw64\\bin\\gcc.exe   -g -o CMakeFiles\\TP.dir\\tp4\\tp4_exo.c.obj -c C:\\Users\\ntrem\\ECE\\Info\\TP\\tp4\\tp4_exo.c",
  "file": "C:/Users/ntrem/ECE/Info/TP/tp4/tp4_exo.c",
  "output": "CMakeFiles/TP.dir/tp4/tp4_exo.c.obj"
},
{
  "directory": "C:/Users/ntrem/ECE/Info/TP/build",
  "command": "C:\\mingw64\\bin\\gcc.exe   -g -o CMakeFiles\\TP.dir\\tp5\\tp5_exo.c.obj -c C:\\Users\\ntrem\\ECE\\Info\\TP\\tp5\\tp5_exo.c",
  "file": "C:/Users/ntrem/ECE/Info/TP/tp5/tp5_exo.c",
  "output": "CMakeFiles/TP.dir/tp5/tp5_exo.c.obj"
},
{
  "directory": "C:/Users/ntrem/ECE/Info/TP/build",
  "command": "C:\\mingw64\\bin\\gcc.exe   -g -o CMakeFiles\\TP.dir\\tp6\\tp6_exo.c.obj -c C:\\Users\\ntrem\\ECE\\Info\\TP\\tp6\\tp6_exo.c",
  "file": "C:/Users/ntrem/ECE/Info/TP/tp6/tp6_exo.c",
  "output": "CMakeFiles/TP.dir/tp6/tp6_exo.c.obj"
},
{
  "directory": "C:/Users/ntrem/ECE/Info/TP/build",
  "command": "C:\\mingw64\\bin\\gcc.exe   -g -o CMakeFiles\\TP.dir\\tp7\\tp7_exo.c.obj -c C:\\Users\\ntrem\\ECE\\Info\\TP\\tp7\\tp7_exo.c",
  "file": "C:/Users/ntrem/ECE/Info/TP/tp7/tp7_exo.c",
  "output": "CMakeFiles/TP.dir/tp7/tp7_exo.c.obj"
},
{
  "directory": "C:/Users/ntrem/ECE/Info/TP/build",
  "command": "C:\\mingw64\\bin\\gcc.exe   -g -o CMakeFiles\\TP.dir\\tp8\\tp8_exo.c.obj -c C:\\Users\\ntrem\\ECE\\Info\\TP\\tp8\\tp8_exo.c",
  "file": "C:/Users/ntrem/ECE/Info/TP/tp8/tp8_exo.c",
  "output": "CMakeFiles/TP.dir/tp8/tp8_exo.c.obj"
},
{
  "directory": "C:/Users/ntrem/ECE/Info/TP/build",
  "command": "C:\\mingw64\\bin\\gcc.exe   -g -o CMakeFiles\\TP.dir\\tp9\\tp9_exo.c.obj -c C:\\Users\\ntrem\\ECE\\Info\\TP\\tp9\\tp9_exo.c",
  "file": "C:/Users/ntrem/ECE/Info/TP/tp9/tp9_exo.c",
  "output": "CMakeFiles/TP.dir/tp9/tp9_exo.c.obj"
}
]